[
  {
    "view": {
      "title": "Type0 Title",
      "subtitle": "This is a subtitle for Type 0",
      "type": "TYPE_0",
      "items": [
        {  "name": "Type0-Item1" },
        {  "name": "Type0-Item2" }
      ]
    }
  },
  {
    "view": {
      "title": "Type1 Title",
      "subtitle": "This is a subtitle for Type 1",
      "type": "TYPE_1",
      "items": [
        {"name": "Type1-Item1" },
        {"name": "Type1-Item2" }
      ]
    }
  },
  {
    "view": {
      "title": "Type2 Title",
      "subtitle": "This is a subtitle for Type 2",
      "type": "TYPE_2",
      "items": [
        { "name": "Type2-Item1" },
        { "name": "Type2-Item2" }
      ]
    }
  },
  {
    "view": {
      "title": "Type3 Title",
      "type": "TYPE_3",
      "subtitle": "This is a subtitle for Type 3",
      "items": [
        { "name": "Type3-Item1" },
        { "name": "Type3-Item2" }
      ]
    }
  },
  {
    "view": {
      "title": "Type4 Title",
      "type": "TYPE_4",
      "subtitle": "This is a subtitle for Type 4",
      "items": [
        { "name": "Type4-Item1" },
        { "name": "Type4-Item2" }
      ]
    }
  },
  {
    "view": {
      "title": "Type5 Title",
      "type": "TYPE_5",
      "subtitle": "This is a subtitle for Type 5",
      "items": [
        { "name": "Type5-Item1" },
        { "name": "Type5-Item2" }
      ]
    }
  }
]
